redcat/__init__.py
redcat/array.py
redcat/base.py
redcat/batchdict.py
redcat/batchlist.py
redcat/comparators.py
redcat/datapipes/__init__.py
redcat/datapipes/iter/__init__.py
redcat/datapipes/iter/batching.py
redcat/datapipes/iter/joining.py
redcat/datapipes/iter/shuffling.py
redcat/return_types.py
redcat/tensor.py
redcat/tensorseq.py
redcat/types.py
redcat/utils/__init__.py
redcat/utils/array.py
redcat/utils/collection.py
redcat/utils/common.py
redcat/utils/random.py
redcat/utils/tensor.py
redcat-0.0.18.dist-info/LICENSE
redcat-0.0.18.dist-info/METADATA
redcat-0.0.18.dist-info/WHEEL
redcat-0.0.18.dist-info/RECORD
