Metadata-Version: 2.1
Name: redcat
Version: 0.0.18
Summary: A library to manipulate batches of examples
Home-page: https://github.com/durandtibo/redcat
License: BSD-3-Clause
Keywords: batch
Author: Thibaut Durand
Author-email: durand.tibo+gh@gmail.com
Requires-Python: >=3.9,<3.12
Classifier: Development Status :: 3 - Alpha
Classifier: Intended Audience :: Developers
Classifier: Intended Audience :: Information Technology
Classifier: Intended Audience :: Science/Research
Classifier: License :: OSI Approved :: BSD License
Classifier: Operating System :: POSIX :: Linux
Classifier: Programming Language :: Python :: 3
Classifier: Programming Language :: Python :: 3.9
Classifier: Programming Language :: Python :: 3.10
Classifier: Programming Language :: Python :: 3.11
Classifier: Topic :: Scientific/Engineering
Classifier: Topic :: Scientific/Engineering :: Artificial Intelligence
Classifier: Topic :: Software Development :: Libraries
Requires-Dist: coola (>=0.0.20,<0.2)
Requires-Dist: numpy (>=1.22,<2.0)
Requires-Dist: torch (>=1.11,<3.0)
Project-URL: Repository, https://github.com/durandtibo/redcat
